LHCbDIRACCommon/__init__.py
LHCbDIRACCommon/ConfigurationSystem/__init__.py
LHCbDIRACCommon/ConfigurationSystem/Client/__init__.py
LHCbDIRACCommon/ConfigurationSystem/Client/Helpers/Resources.py
LHCbDIRACCommon/ConfigurationSystem/Client/Helpers/__init__.py
lhcbdiraccommon-0.0.1.dist-info/METADATA
lhcbdiraccommon-0.0.1.dist-info/WHEEL
lhcbdiraccommon-0.0.1.dist-info/RECORD
