Metadata-Version: 2.4
Name: LHCbDIRACCommon
Version: 0.0.1
Summary: Common utilities and components shared across the LHCb DIRAC ecosystem during the DIRAC → DiracX migration
Author-email: Chris Burr <christopher.burr@cern.ch>
Requires-Python: >=3.11
Requires-Dist: diraccommon<10,>=9.0.0a69
Requires-Dist: lbplatformutils
